<?xml version='1.0' encoding='utf-8'?>
<annotation>
    <folder>/待标.zip/待标</folder>
    <filename>0392.jpg</filename>
    <path>/待标.zip/待标</path>
    <source>
        <database>Unknown</database>
    </source>
    <amount>13</amount>
    <size>
        <width>1920</width>
        <height>1000</height>
        <depth>3</depth>
    </size>
    <segmented>0</segmented>
    <object>
        <name>day-no</name>
        <pose>Unspecified</pose>
        <type>rect</type>
        <truncated>0</truncated>
        <difficult>0</difficult>
        <text>1</text>
        <model>3</model>
        <bndbox>
            <xmin>678</xmin>
            <ymin>425</ymin>
            <xmax>790</xmax>
            <ymax>524</ymax>
        </bndbox>
        <width>112</width>
        <height>99</height>
    </object>
    <object>
        <name>L_light</name>
        <pose>Unspecified</pose>
        <type>rect</type>
        <truncated>0</truncated>
        <difficult>0</difficult>
        <text>1</text>
        <model>3</model>
        <bndbox>
            <xmin>680</xmin>
            <ymin>452</ymin>
            <xmax>708</xmax>
            <ymax>465</ymax>
        </bndbox>
        <width>28</width>
        <height>13</height>
    </object>
    <object>
        <name>R_light</name>
        <pose>Unspecified</pose>
        <type>rect</type>
        <truncated>0</truncated>
        <difficult>0</difficult>
        <text>1</text>
        <model>3</model>
        <bndbox>
            <xmin>750</xmin>
            <ymin>449</ymin>
            <xmax>784</xmax>
            <ymax>462</ymax>
        </bndbox>
        <width>35</width>
        <height>12</height>
    </object>
    <object>
        <name>T_light</name>
        <pose>Unspecified</pose>
        <type>rect</type>
        <truncated>0</truncated>
        <difficult>0</difficult>
        <text>1</text>
        <model>3</model>
        <bndbox>
            <xmin>727</xmin>
            <ymin>429</ymin>
            <xmax>741</xmax>
            <ymax>432</ymax>
        </bndbox>
        <width>14</width>
        <height>3</height>
    </object>
    <object>
        <name>day-no</name>
        <pose>Unspecified</pose>
        <type>rect</type>
        <truncated>0</truncated>
        <difficult>0</difficult>
        <text>2</text>
        <model>3</model>
        <bndbox>
            <xmin>844</xmin>
            <ymin>436</ymin>
            <xmax>895</xmax>
            <ymax>481</ymax>
        </bndbox>
        <width>51</width>
        <height>45</height>
    </object>
    <object>
        <name>L_light</name>
        <pose>Unspecified</pose>
        <type>rect</type>
        <truncated>0</truncated>
        <difficult>0</difficult>
        <text>2</text>
        <model>3</model>
        <bndbox>
            <xmin>845</xmin>
            <ymin>452</ymin>
            <xmax>856</xmax>
            <ymax>459</ymax>
        </bndbox>
        <width>11</width>
        <height>7</height>
    </object>
    <object>
        <name>R_light</name>
        <pose>Unspecified</pose>
        <type>rect</type>
        <truncated>0</truncated>
        <difficult>0</difficult>
        <text>2</text>
        <model>3</model>
        <bndbox>
            <xmin>880</xmin>
            <ymin>450</ymin>
            <xmax>892</xmax>
            <ymax>459</ymax>
        </bndbox>
        <width>12</width>
        <height>8</height>
    </object>
    <object>
        <name>T_light</name>
        <pose>Unspecified</pose>
        <type>rect</type>
        <truncated>0</truncated>
        <difficult>0</difficult>
        <text>2</text>
        <model>3</model>
        <bndbox>
            <xmin>865</xmin>
            <ymin>437</ymin>
            <xmax>876</xmax>
            <ymax>440</ymax>
        </bndbox>
        <width>12</width>
        <height>3</height>
    </object>
    <object>
        <name>day-brake</name>
        <pose>Unspecified</pose>
        <type>rect</type>
        <truncated>0</truncated>
        <difficult>0</difficult>
        <text>3</text>
        <model>3</model>
        <bndbox>
            <xmin>1327</xmin>
            <ymin>395</ymin>
            <xmax>1502</xmax>
            <ymax>575</ymax>
        </bndbox>
        <width>175</width>
        <height>180</height>
    </object>
    <object>
        <name>L_light</name>
        <pose>Unspecified</pose>
        <type>rect</type>
        <truncated>0</truncated>
        <difficult>0</difficult>
        <text>3</text>
        <model>3</model>
        <bndbox>
            <xmin>1327</xmin>
            <ymin>443</ymin>
            <xmax>1386</xmax>
            <ymax>474</ymax>
        </bndbox>
        <width>59</width>
        <height>31</height>
    </object>
    <object>
        <name>R_light</name>
        <pose>Unspecified</pose>
        <type>rect</type>
        <truncated>0</truncated>
        <difficult>0</difficult>
        <text>3</text>
        <model>3</model>
        <bndbox>
            <xmin>1469</xmin>
            <ymin>448</ymin>
            <xmax>1497</xmax>
            <ymax>474</ymax>
        </bndbox>
        <width>29</width>
        <height>25</height>
    </object>
    <object>
        <name>T_light</name>
        <pose>Unspecified</pose>
        <type>rect</type>
        <truncated>0</truncated>
        <difficult>0</difficult>
        <text>3</text>
        <model>3</model>
        <bndbox>
            <xmin>1393</xmin>
            <ymin>404</ymin>
            <xmax>1422</xmax>
            <ymax>412</ymax>
        </bndbox>
        <width>30</width>
        <height>8</height>
    </object>
    <object>
        <name>plate_1</name>
        <pose>Unspecified</pose>
        <type>rect</type>
        <truncated>0</truncated>
        <difficult>0</difficult>
        <text>
        </text>
        <bndbox>
            <xmin>1404</xmin>
            <ymin>470</ymin>
            <xmax>1451</xmax>
            <ymax>490</ymax>
        </bndbox>
        <width>47</width>
        <height>20</height>
    </object>
</annotation>