<?xml version="1.0" encoding="UTF-8"?>
<annotation>
    <folder>/待标.zip/待标</folder>
    <filename>0821c8.jpg</filename>
    <path>/待标.zip/待标</path>
    <source>
        <database>Unknown</database>
    </source>
    <amount>13</amount>
    <size>
        <width>1340</width>
        <height>345</height>
        <depth>3</depth>
    </size>
    <segmented>0</segmented>
    <object>
        <name>night-no</name>
        <pose>Unspecified</pose>
        <type>rect</type>
        <truncated>0</truncated>
        <difficult>0</difficult>
        <text>1</text>
        <model>3</model>
        <bndbox>
            <xmin>172</xmin>
            <ymin>156</ymin>
            <xmax>268</xmax>
            <ymax>254</ymax>
        </bndbox>
        <width>96</width>
        <height>98</height>
    </object>
    <object>
        <name>L_light</name>
        <pose>Unspecified</pose>
        <type>rect</type>
        <truncated>0</truncated>
        <difficult>0</difficult>
        <text>1</text>
        <model>3</model>
        <bndbox>
            <xmin>171</xmin>
            <ymin>191</ymin>
            <xmax>196</xmax>
            <ymax>206</ymax>
        </bndbox>
        <width>24</width>
        <height>15</height>
    </object>
    <object>
        <name>R_light</name>
        <pose>Unspecified</pose>
        <type>rect</type>
        <truncated>0</truncated>
        <difficult>0</difficult>
        <text>1</text>
        <model>3</model>
        <bndbox>
            <xmin>241</xmin>
            <ymin>189</ymin>
            <xmax>267</xmax>
            <ymax>205</ymax>
        </bndbox>
        <width>27</width>
        <height>17</height>
    </object>
    <object>
        <name>T_light</name>
        <pose>Unspecified</pose>
        <type>rect</type>
        <truncated>0</truncated>
        <difficult>0</difficult>
        <text>1</text>
        <model>3</model>
        <bndbox>
            <xmin>219</xmin>
            <ymin>163</ymin>
            <xmax>237</xmax>
            <ymax>167</ymax>
        </bndbox>
        <width>18</width>
        <height>4</height>
    </object>
    <object>
        <name>night-no</name>
        <pose>Unspecified</pose>
        <type>rect</type>
        <truncated>0</truncated>
        <difficult>0</difficult>
        <text>2</text>
        <model>3</model>
        <bndbox>
            <xmin>305</xmin>
            <ymin>124</ymin>
            <xmax>504</xmax>
            <ymax>302</ymax>
        </bndbox>
        <width>199</width>
        <height>178</height>
    </object>
    <object>
        <name>L_light</name>
        <pose>Unspecified</pose>
        <type>rect</type>
        <truncated>0</truncated>
        <difficult>0</difficult>
        <text>2</text>
        <model>3</model>
        <bndbox>
            <xmin>315</xmin>
            <ymin>142</ymin>
            <xmax>342</xmax>
            <ymax>195</ymax>
        </bndbox>
        <width>27</width>
        <height>53</height>
    </object>
    <object>
        <name>R_light</name>
        <pose>Unspecified</pose>
        <type>rect</type>
        <truncated>0</truncated>
        <difficult>0</difficult>
        <text>2</text>
        <model>3</model>
        <bndbox>
            <xmin>465</xmin>
            <ymin>140</ymin>
            <xmax>493</xmax>
            <ymax>191</ymax>
        </bndbox>
        <width>28</width>
        <height>51</height>
    </object>
    <object>
        <name>T_light</name>
        <pose>Unspecified</pose>
        <type>rect</type>
        <truncated>0</truncated>
        <difficult>0</difficult>
        <text>2</text>
        <model>3</model>
        <bndbox>
            <xmin>375</xmin>
            <ymin>125</ymin>
            <xmax>431</xmax>
            <ymax>131</ymax>
        </bndbox>
        <width>56</width>
        <height>6</height>
    </object>
    <object>
        <name>night-right</name>
        <pose>Unspecified</pose>
        <type>rect</type>
        <truncated>0</truncated>
        <difficult>0</difficult>
        <text>3</text>
        <model>3</model>
        <bndbox>
            <xmin>633</xmin>
            <ymin>116</ymin>
            <xmax>751</xmax>
            <ymax>246</ymax>
        </bndbox>
        <width>118</width>
        <height>129</height>
    </object>
    <object>
        <name>L_light</name>
        <pose>Unspecified</pose>
        <type>rect</type>
        <truncated>0</truncated>
        <difficult>0</difficult>
        <text>3</text>
        <model>3</model>
        <bndbox>
            <xmin>634</xmin>
            <ymin>162</ymin>
            <xmax>654</xmax>
            <ymax>195</ymax>
        </bndbox>
        <width>20</width>
        <height>33</height>
    </object>
    <object>
        <name>R_light</name>
        <pose>Unspecified</pose>
        <type>rect</type>
        <truncated>0</truncated>
        <difficult>0</difficult>
        <text>3</text>
        <model>3</model>
        <bndbox>
            <xmin>733</xmin>
            <ymin>166</ymin>
            <xmax>750</xmax>
            <ymax>195</ymax>
        </bndbox>
        <width>17</width>
        <height>29</height>
    </object>
    <object>
        <name>T_light</name>
        <pose>Unspecified</pose>
        <type>rect</type>
        <truncated>0</truncated>
        <difficult>0</difficult>
        <text>3</text>
        <model>3</model>
        <bndbox>
            <xmin>684</xmin>
            <ymin>122</ymin>
            <xmax>705</xmax>
            <ymax>126</ymax>
        </bndbox>
        <width>21</width>
        <height>4</height>
    </object>
    <object>
        <name>plate_1</name>
        <pose>Unspecified</pose>
        <type>rect</type>
        <truncated>0</truncated>
        <difficult>0</difficult>
        <text>3</text>
        <bndbox>
            <xmin>377</xmin>
            <ymin>187</ymin>
            <xmax>431</xmax>
            <ymax>205</ymax>
        </bndbox>
        <width>54</width>
        <height>17</height>
    </object>
</annotation>
