<?xml version='1.0' encoding='utf-8'?>
<annotation>
    <folder>/待标.zip/待标</folder>
    <filename>1109.jpg</filename>
    <path>/待标.zip/待标</path>
    <source>
        <database>Unknown</database>
    </source>
    <amount>12</amount>
    <size>
        <width>960</width>
        <height>1000</height>
        <depth>3</depth>
    </size>
    <segmented>0</segmented>
    <object>
        <name>day-brake</name>
        <pose>Unspecified</pose>
        <type>rect</type>
        <truncated>0</truncated>
        <difficult>0</difficult>
        <text>1</text>
        <model>3</model>
        <bndbox>
            <xmin>671</xmin>
            <ymin>197</ymin>
            <xmax>901</xmax>
            <ymax>405</ymax>
        </bndbox>
        <width>230</width>
        <height>208</height>
    </object>
    <object>
        <name>L_light</name>
        <pose>Unspecified</pose>
        <type>rect</type>
        <truncated>0</truncated>
        <difficult>0</difficult>
        <text>1</text>
        <model>3</model>
        <bndbox>
            <xmin>701</xmin>
            <ymin>273</ymin>
            <xmax>784</xmax>
            <ymax>302</ymax>
        </bndbox>
        <width>83</width>
        <height>29</height>
    </object>
    <object>
        <name>R_light</name>
        <pose>Unspecified</pose>
        <type>rect</type>
        <truncated>0</truncated>
        <difficult>0</difficult>
        <text>1</text>
        <model>3</model>
        <bndbox>
            <xmin>877</xmin>
            <ymin>270</ymin>
            <xmax>900</xmax>
            <ymax>293</ymax>
        </bndbox>
        <width>22</width>
        <height>22</height>
    </object>
    <object>
        <name>T_light</name>
        <pose>Unspecified</pose>
        <type>rect</type>
        <truncated>0</truncated>
        <difficult>0</difficult>
        <text>1</text>
        <model>3</model>
        <bndbox>
            <xmin>738</xmin>
            <ymin>206</ymin>
            <xmax>773</xmax>
            <ymax>212</ymax>
        </bndbox>
        <width>35</width>
        <height>6</height>
    </object>
    <object>
        <name>day-brake</name>
        <pose>Unspecified</pose>
        <type>rect</type>
        <truncated>0</truncated>
        <difficult>0</difficult>
        <text>2</text>
        <model>3</model>
        <bndbox>
            <xmin>330</xmin>
            <ymin>203</ymin>
            <xmax>485</xmax>
            <ymax>334</ymax>
        </bndbox>
        <width>155</width>
        <height>131</height>
    </object>
    <object>
        <name>L_light</name>
        <pose>Unspecified</pose>
        <type>rect</type>
        <truncated>0</truncated>
        <difficult>0</difficult>
        <text>2</text>
        <model>3</model>
        <bndbox>
            <xmin>331</xmin>
            <ymin>250</ymin>
            <xmax>370</xmax>
            <ymax>269</ymax>
        </bndbox>
        <width>39</width>
        <height>19</height>
    </object>
    <object>
        <name>R_light</name>
        <pose>Unspecified</pose>
        <type>rect</type>
        <truncated>0</truncated>
        <difficult>0</difficult>
        <text>2</text>
        <model>3</model>
        <bndbox>
            <xmin>442</xmin>
            <ymin>247</ymin>
            <xmax>484</xmax>
            <ymax>266</ymax>
        </bndbox>
        <width>42</width>
        <height>20</height>
    </object>
    <object>
        <name>T_light</name>
        <pose>Unspecified</pose>
        <type>rect</type>
        <truncated>0</truncated>
        <difficult>0</difficult>
        <text>2</text>
        <model>3</model>
        <bndbox>
            <xmin>398</xmin>
            <ymin>228</ymin>
            <xmax>418</xmax>
            <ymax>232</ymax>
        </bndbox>
        <width>20</width>
        <height>5</height>
    </object>
    <object>
        <name>day-no</name>
        <pose>Unspecified</pose>
        <type>rect</type>
        <truncated>0</truncated>
        <difficult>0</difficult>
        <text>3</text>
        <model>3</model>
        <bndbox>
            <xmin>63</xmin>
            <ymin>211</ymin>
            <xmax>198</xmax>
            <ymax>345</ymax>
        </bndbox>
        <width>134</width>
        <height>135</height>
    </object>
    <object>
        <name>L_light</name>
        <pose>Unspecified</pose>
        <type>rect</type>
        <truncated>0</truncated>
        <difficult>0</difficult>
        <text>3</text>
        <model>3</model>
        <bndbox>
            <xmin>63</xmin>
            <ymin>261</ymin>
            <xmax>92</xmax>
            <ymax>278</ymax>
        </bndbox>
        <width>29</width>
        <height>17</height>
    </object>
    <object>
        <name>R_light</name>
        <pose>Unspecified</pose>
        <type>rect</type>
        <truncated>0</truncated>
        <difficult>0</difficult>
        <text>3</text>
        <model>3</model>
        <bndbox>
            <xmin>140</xmin>
            <ymin>253</ymin>
            <xmax>194</xmax>
            <ymax>276</ymax>
        </bndbox>
        <width>55</width>
        <height>22</height>
    </object>
    <object>
        <name>T_light</name>
        <pose>Unspecified</pose>
        <type>rect</type>
        <truncated>0</truncated>
        <difficult>0</difficult>
        <text>3</text>
        <model>3</model>
        <bndbox>
            <xmin>141</xmin>
            <ymin>219</ymin>
            <xmax>161</xmax>
            <ymax>224</ymax>
        </bndbox>
        <width>21</width>
        <height>5</height>
    </object>
</annotation>