<?xml version='1.0' encoding='utf-8'?>
<annotation>
    <folder>/待标.zip/待标</folder>
    <filename>2364.jpg</filename>
    <path>/待标.zip/待标</path>
    <source>
        <database>Unknown</database>
    </source>
    <amount>8</amount>
    <size>
        <width>960</width>
        <height>1000</height>
        <depth>3</depth>
    </size>
    <segmented>0</segmented>
    <object>
        <name>night-brake</name>
        <pose>Unspecified</pose>
        <type>rect</type>
        <truncated>0</truncated>
        <difficult>0</difficult>
        <text>1</text>
        <model>3</model>
        <bndbox>
            <xmin>324</xmin>
            <ymin>147</ymin>
            <xmax>386</xmax>
            <ymax>202</ymax>
        </bndbox>
        <width>62</width>
        <height>55</height>
    </object>
    <object>
        <name>T_light</name>
        <pose>Unspecified</pose>
        <type>rect</type>
        <truncated>0</truncated>
        <difficult>0</difficult>
        <text>1</text>
        <model>3</model>
        <bndbox>
            <xmin>354</xmin>
            <ymin>150</ymin>
            <xmax>366</xmax>
            <ymax>154</ymax>
        </bndbox>
        <width>13</width>
        <height>5</height>
    </object>
    <object>
        <name>L_light</name>
        <pose>Unspecified</pose>
        <type>rect</type>
        <truncated>0</truncated>
        <difficult>0</difficult>
        <text>1</text>
        <model>3</model>
        <bndbox>
            <xmin>325</xmin>
            <ymin>171</ymin>
            <xmax>341</xmax>
            <ymax>180</ymax>
        </bndbox>
        <width>16</width>
        <height>8</height>
    </object>
    <object>
        <name>R_light</name>
        <pose>Unspecified</pose>
        <type>rect</type>
        <truncated>0</truncated>
        <difficult>0</difficult>
        <text>1</text>
        <model>3</model>
        <bndbox>
            <xmin>366</xmin>
            <ymin>170</ymin>
            <xmax>383</xmax>
            <ymax>179</ymax>
        </bndbox>
        <width>17</width>
        <height>9</height>
    </object>
    <object>
        <name>night-brake</name>
        <pose>Unspecified</pose>
        <type>rect</type>
        <truncated>0</truncated>
        <difficult>0</difficult>
        <text>2</text>
        <model>3</model>
        <bndbox>
            <xmin>441</xmin>
            <ymin>141</ymin>
            <xmax>488</xmax>
            <ymax>183</ymax>
        </bndbox>
        <width>47</width>
        <height>42</height>
    </object>
    <object>
        <name>T_light</name>
        <pose>Unspecified</pose>
        <type>rect</type>
        <truncated>0</truncated>
        <difficult>0</difficult>
        <text>2</text>
        <model>3</model>
        <bndbox>
            <xmin>459</xmin>
            <ymin>142</ymin>
            <xmax>469</xmax>
            <ymax>146</ymax>
        </bndbox>
        <width>10</width>
        <height>3</height>
    </object>
    <object>
        <name>L_light</name>
        <pose>Unspecified</pose>
        <type>rect</type>
        <truncated>0</truncated>
        <difficult>0</difficult>
        <text>2</text>
        <model>3</model>
        <bndbox>
            <xmin>443</xmin>
            <ymin>153</ymin>
            <xmax>453</xmax>
            <ymax>160</ymax>
        </bndbox>
        <width>11</width>
        <height>7</height>
    </object>
    <object>
        <name>R_light</name>
        <pose>Unspecified</pose>
        <type>rect</type>
        <truncated>0</truncated>
        <difficult>0</difficult>
        <text>2</text>
        <model>3</model>
        <bndbox>
            <xmin>474</xmin>
            <ymin>153</ymin>
            <xmax>486</xmax>
            <ymax>160</ymax>
        </bndbox>
        <width>12</width>
        <height>7</height>
    </object>
</annotation>