<?xml version='1.0' encoding='utf-8'?>
<annotation>
    <folder>/待标.zip/待标</folder>
    <filename>2395.jpg</filename>
    <path>/待标.zip/待标</path>
    <source>
        <database>Unknown</database>
    </source>
    <amount>8</amount>
    <size>
        <width>960</width>
        <height>1000</height>
        <depth>3</depth>
    </size>
    <segmented>0</segmented>
    <object>
        <name>night-brake</name>
        <pose>Unspecified</pose>
        <type>rect</type>
        <truncated>0</truncated>
        <difficult>0</difficult>
        <text>1</text>
        <model>3</model>
        <bndbox>
            <xmin>777</xmin>
            <ymin>136</ymin>
            <xmax>924</xmax>
            <ymax>293</ymax>
        </bndbox>
        <width>148</width>
        <height>157</height>
    </object>
    <object>
        <name>L_light</name>
        <pose>Unspecified</pose>
        <type>rect</type>
        <truncated>0</truncated>
        <difficult>0</difficult>
        <text>1</text>
        <model>3</model>
        <bndbox>
            <xmin>807</xmin>
            <ymin>194</ymin>
            <xmax>858</xmax>
            <ymax>220</ymax>
        </bndbox>
        <width>52</width>
        <height>26</height>
    </object>
    <object>
        <name>R_light</name>
        <pose>Unspecified</pose>
        <type>rect</type>
        <truncated>0</truncated>
        <difficult>0</difficult>
        <text>1</text>
        <model>3</model>
        <bndbox>
            <xmin>902</xmin>
            <ymin>208</ymin>
            <xmax>923</xmax>
            <ymax>225</ymax>
        </bndbox>
        <width>20</width>
        <height>17</height>
    </object>
    <object>
        <name>T_light</name>
        <pose>Unspecified</pose>
        <type>rect</type>
        <truncated>0</truncated>
        <difficult>0</difficult>
        <text>1</text>
        <model>3</model>
        <bndbox>
            <xmin>845</xmin>
            <ymin>177</ymin>
            <xmax>864</xmax>
            <ymax>184</ymax>
        </bndbox>
        <width>20</width>
        <height>7</height>
    </object>
    <object>
        <name>night-brake</name>
        <pose>Unspecified</pose>
        <type>rect</type>
        <truncated>0</truncated>
        <difficult>0</difficult>
        <text>2</text>
        <model>3</model>
        <bndbox>
            <xmin>402</xmin>
            <ymin>105</ymin>
            <xmax>586</xmax>
            <ymax>275</ymax>
        </bndbox>
        <width>184</width>
        <height>170</height>
    </object>
    <object>
        <name>L_light</name>
        <pose>Unspecified</pose>
        <type>rect</type>
        <truncated>0</truncated>
        <difficult>0</difficult>
        <text>2</text>
        <model>3</model>
        <bndbox>
            <xmin>411</xmin>
            <ymin>159</ymin>
            <xmax>426</xmax>
            <ymax>196</ymax>
        </bndbox>
        <width>15</width>
        <height>36</height>
    </object>
    <object>
        <name>R_light</name>
        <pose>Unspecified</pose>
        <type>rect</type>
        <truncated>0</truncated>
        <difficult>0</difficult>
        <text>2</text>
        <model>3</model>
        <bndbox>
            <xmin>569</xmin>
            <ymin>160</ymin>
            <xmax>583</xmax>
            <ymax>192</ymax>
        </bndbox>
        <width>14</width>
        <height>32</height>
    </object>
    <object>
        <name>T_light</name>
        <pose>Unspecified</pose>
        <type>rect</type>
        <truncated>0</truncated>
        <difficult>0</difficult>
        <text>2</text>
        <model>3</model>
        <bndbox>
            <xmin>476</xmin>
            <ymin>106</ymin>
            <xmax>512</xmax>
            <ymax>114</ymax>
        </bndbox>
        <width>36</width>
        <height>8</height>
    </object>
</annotation>