<?xml version='1.0' encoding='utf-8'?>
<annotation>
    <folder>/待标.zip/待标</folder>
    <filename>2400.jpg</filename>
    <path>/待标.zip/待标</path>
    <source>
        <database>Unknown</database>
    </source>
    <amount>8</amount>
    <size>
        <width>960</width>
        <height>1000</height>
        <depth>3</depth>
    </size>
    <segmented>0</segmented>
    <object>
        <name>night-brake</name>
        <pose>Unspecified</pose>
        <type>rect</type>
        <truncated>0</truncated>
        <difficult>0</difficult>
        <text>1</text>
        <model>3</model>
        <bndbox>
            <xmin>396</xmin>
            <ymin>97</ymin>
            <xmax>607</xmax>
            <ymax>289</ymax>
        </bndbox>
        <width>211</width>
        <height>192</height>
    </object>
    <object>
        <name>night-no</name>
        <pose>Unspecified</pose>
        <type>rect</type>
        <truncated>0</truncated>
        <difficult>0</difficult>
        <text>1</text>
        <model>3</model>
        <bndbox>
            <xmin>780</xmin>
            <ymin>136</ymin>
            <xmax>941</xmax>
            <ymax>311</ymax>
        </bndbox>
        <width>161</width>
        <height>175</height>
    </object>
    <object>
        <name>L_light</name>
        <pose>Unspecified</pose>
        <type>rect</type>
        <truncated>0</truncated>
        <difficult>0</difficult>
        <text>1</text>
        <model>3</model>
        <bndbox>
            <xmin>406</xmin>
            <ymin>169</ymin>
            <xmax>423</xmax>
            <ymax>205</ymax>
        </bndbox>
        <width>18</width>
        <height>36</height>
    </object>
    <object>
        <name>R_light</name>
        <pose>Unspecified</pose>
        <type>rect</type>
        <truncated>0</truncated>
        <difficult>0</difficult>
        <text>1</text>
        <model>3</model>
        <bndbox>
            <xmin>591</xmin>
            <ymin>166</ymin>
            <xmax>606</xmax>
            <ymax>200</ymax>
        </bndbox>
        <width>15</width>
        <height>34</height>
    </object>
    <object>
        <name>T_light</name>
        <pose>Unspecified</pose>
        <type>rect</type>
        <truncated>0</truncated>
        <difficult>0</difficult>
        <text>2</text>
        <model>3</model>
        <bndbox>
            <xmin>484</xmin>
            <ymin>99</ymin>
            <xmax>523</xmax>
            <ymax>106</ymax>
        </bndbox>
        <width>39</width>
        <height>7</height>
    </object>
    <object>
        <name>L_light</name>
        <pose>Unspecified</pose>
        <type>rect</type>
        <truncated>0</truncated>
        <difficult>0</difficult>
        <text>2</text>
        <model>3</model>
        <bndbox>
            <xmin>816</xmin>
            <ymin>196</ymin>
            <xmax>878</xmax>
            <ymax>227</ymax>
        </bndbox>
        <width>62</width>
        <height>31</height>
    </object>
    <object>
        <name>R_light</name>
        <pose>Unspecified</pose>
        <type>rect</type>
        <truncated>0</truncated>
        <difficult>0</difficult>
        <text>2</text>
        <model>3</model>
        <bndbox>
            <xmin>921</xmin>
            <ymin>213</ymin>
            <xmax>941</xmax>
            <ymax>230</ymax>
        </bndbox>
        <width>20</width>
        <height>17</height>
    </object>
    <object>
        <name>T_light</name>
        <pose>Unspecified</pose>
        <type>rect</type>
        <truncated>0</truncated>
        <difficult>0</difficult>
        <text>2</text>
        <model>3</model>
        <bndbox>
            <xmin>831</xmin>
            <ymin>148</ymin>
            <xmax>850</xmax>
            <ymax>155</ymax>
        </bndbox>
        <width>19</width>
        <height>7</height>
    </object>
</annotation>