<?xml version="1.0" encoding="UTF-8"?>
<annotation>
    <folder>/待标.zip/待标</folder>
    <filename>2452c9f.jpg</filename>
    <path>/待标.zip/待标</path>
    <source>
        <database>Unknown</database>
    </source>
    <amount>4</amount>
    <size>
        <width>266</width>
        <height>120</height>
        <depth>3</depth>
    </size>
    <segmented>0</segmented>
    <object>
        <name>night-right</name>
        <pose>Unspecified</pose>
        <type>rect</type>
        <truncated>0</truncated>
        <difficult>0</difficult>
        <text>1</text>
        <model>3</model>
        <bndbox>
            <xmin>149</xmin>
            <ymin>42</ymin>
            <xmax>190</xmax>
            <ymax>78</ymax>
        </bndbox>
        <width>41</width>
        <height>36</height>
    </object>
    <object>
        <name>L_light</name>
        <pose>Unspecified</pose>
        <type>rect</type>
        <truncated>0</truncated>
        <difficult>0</difficult>
        <text>1</text>
        <model>3</model>
        <bndbox>
            <xmin>150</xmin>
            <ymin>55</ymin>
            <xmax>157</xmax>
            <ymax>64</ymax>
        </bndbox>
        <width>7</width>
        <height>9</height>
    </object>
    <object>
        <name>R_light</name>
        <pose>Unspecified</pose>
        <type>rect</type>
        <truncated>0</truncated>
        <difficult>0</difficult>
        <text>1</text>
        <model>3</model>
        <bndbox>
            <xmin>183</xmin>
            <ymin>57</ymin>
            <xmax>189</xmax>
            <ymax>66</ymax>
        </bndbox>
        <width>7</width>
        <height>9</height>
    </object>
    <object>
        <name>T_light</name>
        <pose>Unspecified</pose>
        <type>rect</type>
        <truncated>0</truncated>
        <difficult>0</difficult>
        <text>1</text>
        <model>3</model>
        <bndbox>
            <xmin>164</xmin>
            <ymin>44</ymin>
            <xmax>171</xmax>
            <ymax>45</ymax>
        </bndbox>
        <width>7</width>
        <height>1</height>
    </object>
</annotation>
