<?xml version="1.0" encoding="UTF-8"?>
<annotation>
    <folder>/待标.zip/待标</folder>
    <filename>2935c6f.jpg</filename>
    <path>/待标.zip/待标</path>
    <source>
        <database>Unknown</database>
    </source>
    <amount>8</amount>
    <size>
        <width>618</width>
        <height>226</height>
        <depth>3</depth>
    </size>
    <segmented>0</segmented>
    <object>
        <name>night-no</name>
        <pose>Unspecified</pose>
        <type>rect</type>
        <truncated>0</truncated>
        <difficult>0</difficult>
        <text>1</text>
        <model>3</model>
        <bndbox>
            <xmin>81</xmin>
            <ymin>7</ymin>
            <xmax>112</xmax>
            <ymax>35</ymax>
        </bndbox>
        <width>31</width>
        <height>28</height>
    </object>
    <object>
        <name>L_light</name>
        <pose>Unspecified</pose>
        <type>rect</type>
        <truncated>0</truncated>
        <difficult>0</difficult>
        <text>1</text>
        <model>3</model>
        <bndbox>
            <xmin>81</xmin>
            <ymin>17</ymin>
            <xmax>85</xmax>
            <ymax>22</ymax>
        </bndbox>
        <width>4</width>
        <height>4</height>
    </object>
    <object>
        <name>R_light</name>
        <pose>Unspecified</pose>
        <type>rect</type>
        <truncated>0</truncated>
        <difficult>0</difficult>
        <text>1</text>
        <model>3</model>
        <bndbox>
            <xmin>103</xmin>
            <ymin>16</ymin>
            <xmax>109</xmax>
            <ymax>21</ymax>
        </bndbox>
        <width>5</width>
        <height>5</height>
    </object>
    <object>
        <name>T_light</name>
        <pose>Unspecified</pose>
        <type>rect</type>
        <truncated>0</truncated>
        <difficult>0</difficult>
        <text>1</text>
        <model>3</model>
        <bndbox>
            <xmin>100</xmin>
            <ymin>9</ymin>
            <xmax>105</xmax>
            <ymax>11</ymax>
        </bndbox>
        <width>4</width>
        <height>2</height>
    </object>
    <object>
        <name>night-right</name>
        <pose>Unspecified</pose>
        <type>rect</type>
        <truncated>0</truncated>
        <difficult>0</difficult>
        <text>2</text>
        <model>3</model>
        <bndbox>
            <xmin>318</xmin>
            <ymin>4</ymin>
            <xmax>361</xmax>
            <ymax>39</ymax>
        </bndbox>
        <width>44</width>
        <height>35</height>
    </object>
    <object>
        <name>L_light</name>
        <pose>Unspecified</pose>
        <type>rect</type>
        <truncated>0</truncated>
        <difficult>0</difficult>
        <text>2</text>
        <model>3</model>
        <bndbox>
            <xmin>319</xmin>
            <ymin>15</ymin>
            <xmax>325</xmax>
            <ymax>21</ymax>
        </bndbox>
        <width>6</width>
        <height>6</height>
    </object>
    <object>
        <name>R_light</name>
        <pose>Unspecified</pose>
        <type>rect</type>
        <truncated>0</truncated>
        <difficult>0</difficult>
        <text>2</text>
        <model>3</model>
        <bndbox>
            <xmin>354</xmin>
            <ymin>17</ymin>
            <xmax>360</xmax>
            <ymax>23</ymax>
        </bndbox>
        <width>6</width>
        <height>6</height>
    </object>
    <object>
        <name>T_light</name>
        <pose>Unspecified</pose>
        <type>rect</type>
        <truncated>0</truncated>
        <difficult>0</difficult>
        <text>2</text>
        <model>3</model>
        <bndbox>
            <xmin>336</xmin>
            <ymin>6</ymin>
            <xmax>342</xmax>
            <ymax>9</ymax>
        </bndbox>
        <width>6</width>
        <height>2</height>
    </object>
</annotation>
