<?xml version="1.0" encoding="UTF-8"?>
<annotation>
    <folder>/待标.zip/待标</folder>
    <filename>2954c8f.jpg</filename>
    <path>/待标.zip/待标</path>
    <source>
        <database>Unknown</database>
    </source>
    <amount>15</amount>
    <size>
        <width>883</width>
        <height>278</height>
        <depth>3</depth>
    </size>
    <segmented>0</segmented>
    <object>
        <name>night-no</name>
        <pose>Unspecified</pose>
        <type>rect</type>
        <truncated>0</truncated>
        <difficult>0</difficult>
        <text>4</text>
        <model>1</model>
        <bndbox>
            <xmin>451</xmin>
            <ymin>6</ymin>
            <xmax>521</xmax>
            <ymax>104</ymax>
        </bndbox>
        <width>70</width>
        <height>99</height>
    </object>
    <object>
        <name>L_light</name>
        <pose>Unspecified</pose>
        <type>rect</type>
        <truncated>0</truncated>
        <difficult>0</difficult>
        <text>1</text>
        <model>1</model>
        <bndbox>
            <xmin>457</xmin>
            <ymin>78</ymin>
            <xmax>468</xmax>
            <ymax>84</ymax>
        </bndbox>
        <width>12</width>
        <height>7</height>
    </object>
    <object>
        <name>R_light</name>
        <pose>Unspecified</pose>
        <type>rect</type>
        <truncated>0</truncated>
        <difficult>0</difficult>
        <text>1</text>
        <model>1</model>
        <bndbox>
            <xmin>500</xmin>
            <ymin>78</ymin>
            <xmax>512</xmax>
            <ymax>85</ymax>
        </bndbox>
        <width>13</width>
        <height>7</height>
    </object>
    <object>
        <name>T_light</name>
        <pose>Unspecified</pose>
        <type>rect</type>
        <truncated>0</truncated>
        <difficult>0</difficult>
        <text>1</text>
        <model>1</model>
        <bndbox>
            <xmin>481</xmin>
            <ymin>10</ymin>
            <xmax>493</xmax>
            <ymax>16</ymax>
        </bndbox>
        <width>13</width>
        <height>6</height>
    </object>
    <object>
        <name>night-no</name>
        <pose>Unspecified</pose>
        <type>rect</type>
        <truncated>0</truncated>
        <difficult>0</difficult>
        <text>2</text>
        <model>3</model>
        <bndbox>
            <xmin>550</xmin>
            <ymin>58</ymin>
            <xmax>598</xmax>
            <ymax>98</ymax>
        </bndbox>
        <width>48</width>
        <height>40</height>
    </object>
    <object>
        <name>L_light</name>
        <pose>Unspecified</pose>
        <type>rect</type>
        <truncated>0</truncated>
        <difficult>0</difficult>
        <text>2</text>
        <model>3</model>
        <bndbox>
            <xmin>553</xmin>
            <ymin>70</ymin>
            <xmax>568</xmax>
            <ymax>78</ymax>
        </bndbox>
        <width>15</width>
        <height>8</height>
    </object>
    <object>
        <name>R_light</name>
        <pose>Unspecified</pose>
        <type>rect</type>
        <truncated>0</truncated>
        <difficult>0</difficult>
        <text>2</text>
        <model>3</model>
        <bndbox>
            <xmin>586</xmin>
            <ymin>73</ymin>
            <xmax>597</xmax>
            <ymax>80</ymax>
        </bndbox>
        <width>11</width>
        <height>7</height>
    </object>
    <object>
        <name>T_light</name>
        <pose>Unspecified</pose>
        <type>rect</type>
        <truncated>0</truncated>
        <difficult>0</difficult>
        <text>2</text>
        <model>3</model>
        <bndbox>
            <xmin>568</xmin>
            <ymin>61</ymin>
            <xmax>578</xmax>
            <ymax>64</ymax>
        </bndbox>
        <width>10</width>
        <height>3</height>
    </object>
    <object>
        <name>night-left</name>
        <pose>Unspecified</pose>
        <type>rect</type>
        <truncated>0</truncated>
        <difficult>0</difficult>
        <text>3</text>
        <model>3</model>
        <bndbox>
            <xmin>643</xmin>
            <ymin>59</ymin>
            <xmax>736</xmax>
            <ymax>144</ymax>
        </bndbox>
        <width>93</width>
        <height>85</height>
    </object>
    <object>
        <name>L_light</name>
        <pose>Unspecified</pose>
        <type>rect</type>
        <truncated>0</truncated>
        <difficult>0</difficult>
        <text>3</text>
        <model>3</model>
        <bndbox>
            <xmin>649</xmin>
            <ymin>86</ymin>
            <xmax>673</xmax>
            <ymax>100</ymax>
        </bndbox>
        <width>24</width>
        <height>14</height>
    </object>
    <object>
        <name>R_light</name>
        <pose>Unspecified</pose>
        <type>rect</type>
        <truncated>0</truncated>
        <difficult>0</difficult>
        <text>3</text>
        <model>3</model>
        <bndbox>
            <xmin>722</xmin>
            <ymin>91</ymin>
            <xmax>735</xmax>
            <ymax>105</ymax>
        </bndbox>
        <width>13</width>
        <height>14</height>
    </object>
    <object>
        <name>T_light</name>
        <pose>Unspecified</pose>
        <type>rect</type>
        <truncated>0</truncated>
        <difficult>0</difficult>
        <text>3</text>
        <model>3</model>
        <bndbox>
            <xmin>673</xmin>
            <ymin>64</ymin>
            <xmax>688</xmax>
            <ymax>69</ymax>
        </bndbox>
        <width>15</width>
        <height>5</height>
    </object>
    <object>
        <name>night-no</name>
        <pose>Unspecified</pose>
        <type>rect</type>
        <truncated>0</truncated>
        <difficult>0</difficult>
        <text>4</text>
        <model>3</model>
        <bndbox>
            <xmin>737</xmin>
            <ymin>61</ymin>
            <xmax>801</xmax>
            <ymax>128</ymax>
        </bndbox>
        <width>64</width>
        <height>68</height>
    </object>
    <object>
        <name>L_light</name>
        <pose>Unspecified</pose>
        <type>rect</type>
        <truncated>0</truncated>
        <difficult>0</difficult>
        <text>4</text>
        <model>3</model>
        <bndbox>
            <xmin>740</xmin>
            <ymin>84</ymin>
            <xmax>766</xmax>
            <ymax>99</ymax>
        </bndbox>
        <width>26</width>
        <height>15</height>
    </object>
    <object>
        <name>R_light</name>
        <pose>Unspecified</pose>
        <type>rect</type>
        <truncated>0</truncated>
        <difficult>0</difficult>
        <text>4</text>
        <model>3</model>
        <bndbox>
            <xmin>786</xmin>
            <ymin>93</ymin>
            <xmax>800</xmax>
            <ymax>103</ymax>
        </bndbox>
        <width>14</width>
        <height>10</height>
    </object>
</annotation>
