<?xml version='1.0' encoding='utf-8'?>
<annotation>
    <folder>/待标.zip/待标</folder>
    <filename>3991.jpg</filename>
    <path>/待标.zip/待标</path>
    <source>
        <database>Unknown</database>
    </source>
    <amount>18</amount>
    <size>
        <width>960</width>
        <height>1000</height>
        <depth>3</depth>
    </size>
    <segmented>0</segmented>
    <object>
        <name>day-no</name>
        <pose>Unspecified</pose>
        <type>rect</type>
        <truncated>0</truncated>
        <difficult>0</difficult>
        <text>1</text>
        <model>3</model>
        <bndbox>
            <xmin>300</xmin>
            <ymin>149</ymin>
            <xmax>353</xmax>
            <ymax>196</ymax>
        </bndbox>
        <width>53</width>
        <height>48</height>
    </object>
    <object>
        <name>L_light</name>
        <pose>Unspecified</pose>
        <type>rect</type>
        <truncated>0</truncated>
        <difficult>0</difficult>
        <text>1</text>
        <model>3</model>
        <bndbox>
            <xmin>302</xmin>
            <ymin>164</ymin>
            <xmax>314</xmax>
            <ymax>171</ymax>
        </bndbox>
        <width>12</width>
        <height>7</height>
    </object>
    <object>
        <name>R_light</name>
        <pose>Unspecified</pose>
        <type>rect</type>
        <truncated>0</truncated>
        <difficult>0</difficult>
        <text>1</text>
        <model>3</model>
        <bndbox>
            <xmin>335</xmin>
            <ymin>164</ymin>
            <xmax>350</xmax>
            <ymax>171</ymax>
        </bndbox>
        <width>15</width>
        <height>7</height>
    </object>
    <object>
        <name>T_light</name>
        <pose>Unspecified</pose>
        <type>rect</type>
        <truncated>0</truncated>
        <difficult>0</difficult>
        <text>1</text>
        <model>3</model>
        <bndbox>
            <xmin>326</xmin>
            <ymin>151</ymin>
            <xmax>336</xmax>
            <ymax>153</ymax>
        </bndbox>
        <width>9</width>
        <height>2</height>
    </object>
    <object>
        <name>day-no</name>
        <pose>Unspecified</pose>
        <type>rect</type>
        <truncated>0</truncated>
        <difficult>0</difficult>
        <text>2</text>
        <model>3</model>
        <bndbox>
            <xmin>414</xmin>
            <ymin>139</ymin>
            <xmax>493</xmax>
            <ymax>206</ymax>
        </bndbox>
        <width>79</width>
        <height>67</height>
    </object>
    <object>
        <name>L_light</name>
        <pose>Unspecified</pose>
        <type>rect</type>
        <truncated>0</truncated>
        <difficult>0</difficult>
        <text>2</text>
        <model>3</model>
        <bndbox>
            <xmin>418</xmin>
            <ymin>157</ymin>
            <xmax>437</xmax>
            <ymax>164</ymax>
        </bndbox>
        <width>19</width>
        <height>8</height>
    </object>
    <object>
        <name>R_light</name>
        <pose>Unspecified</pose>
        <type>rect</type>
        <truncated>0</truncated>
        <difficult>0</difficult>
        <text>2</text>
        <model>3</model>
        <bndbox>
            <xmin>473</xmin>
            <ymin>156</ymin>
            <xmax>490</xmax>
            <ymax>164</ymax>
        </bndbox>
        <width>17</width>
        <height>7</height>
    </object>
    <object>
        <name>T_light</name>
        <pose>Unspecified</pose>
        <type>rect</type>
        <truncated>0</truncated>
        <difficult>0</difficult>
        <text>2</text>
        <model>3</model>
        <bndbox>
            <xmin>450</xmin>
            <ymin>157</ymin>
            <xmax>462</xmax>
            <ymax>159</ymax>
        </bndbox>
        <width>12</width>
        <height>2</height>
    </object>
    <object>
        <name>day-no</name>
        <pose>Unspecified</pose>
        <type>rect</type>
        <truncated>0</truncated>
        <difficult>0</difficult>
        <text>3</text>
        <model>3</model>
        <bndbox>
            <xmin>547</xmin>
            <ymin>141</ymin>
            <xmax>606</xmax>
            <ymax>194</ymax>
        </bndbox>
        <width>58</width>
        <height>53</height>
    </object>
    <object>
        <name>L_light</name>
        <pose>Unspecified</pose>
        <type>rect</type>
        <truncated>0</truncated>
        <difficult>0</difficult>
        <text>3</text>
        <model>3</model>
        <bndbox>
            <xmin>548</xmin>
            <ymin>155</ymin>
            <xmax>560</xmax>
            <ymax>166</ymax>
        </bndbox>
        <width>11</width>
        <height>10</height>
    </object>
    <object>
        <name>R_light</name>
        <pose>Unspecified</pose>
        <type>rect</type>
        <truncated>0</truncated>
        <difficult>0</difficult>
        <text>3</text>
        <model>3</model>
        <bndbox>
            <xmin>597</xmin>
            <ymin>158</ymin>
            <xmax>604</xmax>
            <ymax>166</ymax>
        </bndbox>
        <width>8</width>
        <height>8</height>
    </object>
    <object>
        <name>T_light</name>
        <pose>Unspecified</pose>
        <type>rect</type>
        <truncated>0</truncated>
        <difficult>0</difficult>
        <text>3</text>
        <model>3</model>
        <bndbox>
            <xmin>567</xmin>
            <ymin>144</ymin>
            <xmax>576</xmax>
            <ymax>145</ymax>
        </bndbox>
        <width>10</width>
        <height>2</height>
    </object>
    <object>
        <name>day-no</name>
        <pose>Unspecified</pose>
        <type>rect</type>
        <truncated>0</truncated>
        <difficult>0</difficult>
        <text>4</text>
        <model>3</model>
        <bndbox>
            <xmin>769</xmin>
            <ymin>145</ymin>
            <xmax>933</xmax>
            <ymax>295</ymax>
        </bndbox>
        <width>164</width>
        <height>151</height>
    </object>
    <object>
        <name>L_light</name>
        <pose>Unspecified</pose>
        <type>rect</type>
        <truncated>0</truncated>
        <difficult>0</difficult>
        <text>4</text>
        <model>3</model>
        <bndbox>
            <xmin>799</xmin>
            <ymin>201</ymin>
            <xmax>865</xmax>
            <ymax>230</ymax>
        </bndbox>
        <width>66</width>
        <height>28</height>
    </object>
    <object>
        <name>R_light</name>
        <pose>Unspecified</pose>
        <type>rect</type>
        <truncated>0</truncated>
        <difficult>0</difficult>
        <text>4</text>
        <model>3</model>
        <bndbox>
            <xmin>905</xmin>
            <ymin>208</ymin>
            <xmax>929</xmax>
            <ymax>231</ymax>
        </bndbox>
        <width>24</width>
        <height>23</height>
    </object>
    <object>
        <name>T_light</name>
        <pose>Unspecified</pose>
        <type>rect</type>
        <truncated>0</truncated>
        <difficult>0</difficult>
        <text>4</text>
        <model>3</model>
        <bndbox>
            <xmin>808</xmin>
            <ymin>150</ymin>
            <xmax>830</xmax>
            <ymax>155</ymax>
        </bndbox>
        <width>23</width>
        <height>4</height>
    </object>
    <object>
        <name>plate_1</name>
        <pose>Unspecified</pose>
        <type>rect</type>
        <truncated>0</truncated>
        <difficult>0</difficult>
        <text>
        </text>
        <bndbox>
            <xmin>36</xmin>
            <ymin>263</ymin>
            <xmax>69</xmax>
            <ymax>278</ymax>
        </bndbox>
        <width>33</width>
        <height>14</height>
    </object>
    <object>
        <name>plate_2</name>
        <pose>Unspecified</pose>
        <type>rect</type>
        <truncated>0</truncated>
        <difficult>0</difficult>
        <text>
        </text>
        <bndbox>
            <xmin>871</xmin>
            <ymin>224</ymin>
            <xmax>906</xmax>
            <ymax>238</ymax>
        </bndbox>
        <width>35</width>
        <height>14</height>
    </object>
</annotation>