<?xml version="1.0" encoding="UTF-8"?>
<annotation>
    <folder>/待标.zip/待标</folder>
    <filename>4212c1.jpg</filename>
    <path>/待标.zip/待标</path>
    <source>
        <database>Unknown</database>
    </source>
    <amount>4</amount>
    <size>
        <width>974</width>
        <height>459</height>
        <depth>3</depth>
    </size>
    <segmented>0</segmented>
    <object>
        <name>day-left</name>
        <pose>Unspecified</pose>
        <type>rect</type>
        <truncated>0</truncated>
        <difficult>0</difficult>
        <text>1</text>
        <model>3</model>
        <bndbox>
            <xmin>284</xmin>
            <ymin>275</ymin>
            <xmax>428</xmax>
            <ymax>392</ymax>
        </bndbox>
        <width>144</width>
        <height>117</height>
    </object>
    <object>
        <name>L_light</name>
        <pose>Unspecified</pose>
        <type>rect</type>
        <truncated>0</truncated>
        <difficult>0</difficult>
        <text>1</text>
        <model>3</model>
        <bndbox>
            <xmin>293</xmin>
            <ymin>319</ymin>
            <xmax>329</xmax>
            <ymax>331</ymax>
        </bndbox>
        <width>35</width>
        <height>12</height>
    </object>
    <object>
        <name>R_light</name>
        <pose>Unspecified</pose>
        <type>rect</type>
        <truncated>0</truncated>
        <difficult>0</difficult>
        <text>1</text>
        <model>3</model>
        <bndbox>
            <xmin>390</xmin>
            <ymin>319</ymin>
            <xmax>424</xmax>
            <ymax>332</ymax>
        </bndbox>
        <width>34</width>
        <height>13</height>
    </object>
    <object>
        <name>T_light</name>
        <pose>Unspecified</pose>
        <type>rect</type>
        <truncated>0</truncated>
        <difficult>0</difficult>
        <text>1</text>
        <model>3</model>
        <bndbox>
            <xmin>345</xmin>
            <ymin>284</ymin>
            <xmax>367</xmax>
            <ymax>288</ymax>
        </bndbox>
        <width>22</width>
        <height>4</height>
    </object>
</annotation>
