<?xml version="1.0" encoding="UTF-8"?>
<annotation>
    <folder>/待标.zip/待标</folder>
    <filename>4232c6f.jpg</filename>
    <path>/待标.zip/待标</path>
    <source>
        <database>Unknown</database>
    </source>
    <amount>8</amount>
    <size>
        <width>1476</width>
        <height>277</height>
        <depth>3</depth>
    </size>
    <segmented>0</segmented>
    <object>
        <name>night-left</name>
        <pose>Unspecified</pose>
        <type>rect</type>
        <truncated>0</truncated>
        <difficult>0</difficult>
        <text>1</text>
        <model>3</model>
        <bndbox>
            <xmin>327</xmin>
            <ymin>100</ymin>
            <xmax>448</xmax>
            <ymax>229</ymax>
        </bndbox>
        <width>120</width>
        <height>129</height>
    </object>
    <object>
        <name>T_light</name>
        <pose>Unspecified</pose>
        <type>rect</type>
        <truncated>0</truncated>
        <difficult>0</difficult>
        <text>1</text>
        <model>3</model>
        <bndbox>
            <xmin>381</xmin>
            <ymin>114</ymin>
            <xmax>400</xmax>
            <ymax>118</ymax>
        </bndbox>
        <width>19</width>
        <height>4</height>
    </object>
    <object>
        <name>L_light</name>
        <pose>Unspecified</pose>
        <type>rect</type>
        <truncated>0</truncated>
        <difficult>0</difficult>
        <text>1</text>
        <model>3</model>
        <bndbox>
            <xmin>331</xmin>
            <ymin>179</ymin>
            <xmax>353</xmax>
            <ymax>191</ymax>
        </bndbox>
        <width>22</width>
        <height>11</height>
    </object>
    <object>
        <name>R_light</name>
        <pose>Unspecified</pose>
        <type>rect</type>
        <truncated>0</truncated>
        <difficult>0</difficult>
        <text>1</text>
        <model>3</model>
        <bndbox>
            <xmin>424</xmin>
            <ymin>179</ymin>
            <xmax>447</xmax>
            <ymax>192</ymax>
        </bndbox>
        <width>23</width>
        <height>12</height>
    </object>
    <object>
        <name>night-brake</name>
        <pose>Unspecified</pose>
        <type>rect</type>
        <truncated>0</truncated>
        <difficult>0</difficult>
        <text>2</text>
        <model>3</model>
        <bndbox>
            <xmin>448</xmin>
            <ymin>95</ymin>
            <xmax>897</xmax>
            <ymax>277</ymax>
        </bndbox>
        <width>449</width>
        <height>182</height>
    </object>
    <object>
        <name>T_light</name>
        <pose>Unspecified</pose>
        <type>rect</type>
        <truncated>0</truncated>
        <difficult>0</difficult>
        <text>2</text>
        <model>3</model>
        <bndbox>
            <xmin>648</xmin>
            <ymin>173</ymin>
            <xmax>701</xmax>
            <ymax>188</ymax>
        </bndbox>
        <width>53</width>
        <height>15</height>
    </object>
    <object>
        <name>L_light</name>
        <pose>Unspecified</pose>
        <type>rect</type>
        <truncated>0</truncated>
        <difficult>0</difficult>
        <text>2</text>
        <model>3</model>
        <bndbox>
            <xmin>449</xmin>
            <ymin>236</ymin>
            <xmax>566</xmax>
            <ymax>277</ymax>
        </bndbox>
        <width>117</width>
        <height>41</height>
    </object>
    <object>
        <name>R_light</name>
        <pose>Unspecified</pose>
        <type>rect</type>
        <truncated>0</truncated>
        <difficult>0</difficult>
        <text>2</text>
        <model>3</model>
        <bndbox>
            <xmin>795</xmin>
            <ymin>237</ymin>
            <xmax>896</xmax>
            <ymax>277</ymax>
        </bndbox>
        <width>101</width>
        <height>40</height>
    </object>
</annotation>
