<?xml version="1.0" encoding="UTF-8"?>
<annotation>
    <folder>/待标.zip/待标</folder>
    <filename>4357c4.jpg</filename>
    <path>/待标.zip/待标</path>
    <source>
        <database>Unknown</database>
    </source>
    <amount>4</amount>
    <size>
        <width>590</width>
        <height>691</height>
        <depth>3</depth>
    </size>
    <segmented>0</segmented>
    <object>
        <name>night-right</name>
        <pose>Unspecified</pose>
        <type>rect</type>
        <truncated>0</truncated>
        <difficult>0</difficult>
        <text>1</text>
        <model>3</model>
        <bndbox>
            <xmin>342</xmin>
            <ymin>248</ymin>
            <xmax>494</xmax>
            <ymax>370</ymax>
        </bndbox>
        <width>151</width>
        <height>122</height>
    </object>
    <object>
        <name>L_light</name>
        <pose>Unspecified</pose>
        <type>rect</type>
        <truncated>0</truncated>
        <difficult>0</difficult>
        <text>1</text>
        <model>3</model>
        <bndbox>
            <xmin>345</xmin>
            <ymin>266</ymin>
            <xmax>387</xmax>
            <ymax>309</ymax>
        </bndbox>
        <width>42</width>
        <height>43</height>
    </object>
    <object>
        <name>R_light</name>
        <pose>Unspecified</pose>
        <type>rect</type>
        <truncated>0</truncated>
        <difficult>0</difficult>
        <text>1</text>
        <model>3</model>
        <bndbox>
            <xmin>447</xmin>
            <ymin>267</ymin>
            <xmax>490</xmax>
            <ymax>311</ymax>
        </bndbox>
        <width>43</width>
        <height>43</height>
    </object>
    <object>
        <name>T_light</name>
        <pose>Unspecified</pose>
        <type>rect</type>
        <truncated>0</truncated>
        <difficult>0</difficult>
        <text>1</text>
        <model>3</model>
        <bndbox>
            <xmin>408</xmin>
            <ymin>253</ymin>
            <xmax>431</xmax>
            <ymax>259</ymax>
        </bndbox>
        <width>23</width>
        <height>6</height>
    </object>
</annotation>
