<?xml version="1.0" encoding="UTF-8"?>
<annotation>
    <folder>/待标.zip/待标</folder>
    <filename>4669c1f.jpg</filename>
    <path>/待标.zip/待标</path>
    <source>
        <database>Unknown</database>
    </source>
    <amount>8</amount>
    <size>
        <width>681</width>
        <height>827</height>
        <depth>3</depth>
    </size>
    <segmented>0</segmented>
    <object>
        <name>day-right</name>
        <pose>Unspecified</pose>
        <type>rect</type>
        <truncated>0</truncated>
        <difficult>0</difficult>
        <text>1</text>
        <model>3</model>
        <bndbox>
            <xmin>37</xmin>
            <ymin>282</ymin>
            <xmax>146</xmax>
            <ymax>389</ymax>
        </bndbox>
        <width>109</width>
        <height>108</height>
    </object>
    <object>
        <name>L_light</name>
        <pose>Unspecified</pose>
        <type>rect</type>
        <truncated>0</truncated>
        <difficult>0</difficult>
        <text>1</text>
        <model>3</model>
        <bndbox>
            <xmin>39</xmin>
            <ymin>310</ymin>
            <xmax>61</xmax>
            <ymax>324</ymax>
        </bndbox>
        <width>22</width>
        <height>14</height>
    </object>
    <object>
        <name>R_light</name>
        <pose>Unspecified</pose>
        <type>rect</type>
        <truncated>0</truncated>
        <difficult>0</difficult>
        <text>1</text>
        <model>3</model>
        <bndbox>
            <xmin>117</xmin>
            <ymin>309</ymin>
            <xmax>146</xmax>
            <ymax>324</ymax>
        </bndbox>
        <width>29</width>
        <height>15</height>
    </object>
    <object>
        <name>T_light</name>
        <pose>Unspecified</pose>
        <type>rect</type>
        <truncated>0</truncated>
        <difficult>0</difficult>
        <text>1</text>
        <model>3</model>
        <bndbox>
            <xmin>81</xmin>
            <ymin>285</ymin>
            <xmax>104</xmax>
            <ymax>288</ymax>
        </bndbox>
        <width>24</width>
        <height>3</height>
    </object>
    <object>
        <name>day-no</name>
        <pose>Unspecified</pose>
        <type>rect</type>
        <truncated>0</truncated>
        <difficult>0</difficult>
        <text>2</text>
        <model>3</model>
        <bndbox>
            <xmin>261</xmin>
            <ymin>299</ymin>
            <xmax>349</xmax>
            <ymax>372</ymax>
        </bndbox>
        <width>88</width>
        <height>73</height>
    </object>
    <object>
        <name>L_light</name>
        <pose>Unspecified</pose>
        <type>rect</type>
        <truncated>0</truncated>
        <difficult>0</difficult>
        <text>2</text>
        <model>3</model>
        <bndbox>
            <xmin>265</xmin>
            <ymin>322</ymin>
            <xmax>289</xmax>
            <ymax>333</ymax>
        </bndbox>
        <width>24</width>
        <height>11</height>
    </object>
    <object>
        <name>R_light</name>
        <pose>Unspecified</pose>
        <type>rect</type>
        <truncated>0</truncated>
        <difficult>0</difficult>
        <text>2</text>
        <model>3</model>
        <bndbox>
            <xmin>323</xmin>
            <ymin>324</ymin>
            <xmax>347</xmax>
            <ymax>333</ymax>
        </bndbox>
        <width>23</width>
        <height>9</height>
    </object>
    <object>
        <name>T_light</name>
        <pose>Unspecified</pose>
        <type>rect</type>
        <truncated>0</truncated>
        <difficult>0</difficult>
        <text>2</text>
        <model>3</model>
        <bndbox>
            <xmin>299</xmin>
            <ymin>303</ymin>
            <xmax>313</xmax>
            <ymax>306</ymax>
        </bndbox>
        <width>13</width>
        <height>3</height>
    </object>
</annotation>
