<?xml version="1.0" encoding="UTF-8"?>
<annotation>
    <folder>/待标.zip/待标</folder>
    <filename>4708c8f.jpg</filename>
    <path>/待标.zip/待标</path>
    <source>
        <database>Unknown</database>
    </source>
    <amount>9</amount>
    <size>
        <width>935</width>
        <height>809</height>
        <depth>3</depth>
    </size>
    <segmented>0</segmented>
    <object>
        <name>day-no</name>
        <pose>Unspecified</pose>
        <type>rect</type>
        <truncated>0</truncated>
        <difficult>0</difficult>
        <text>1</text>
        <model>3</model>
        <bndbox>
            <xmin>203</xmin>
            <ymin>286</ymin>
            <xmax>265</xmax>
            <ymax>338</ymax>
        </bndbox>
        <width>61</width>
        <height>52</height>
    </object>
    <object>
        <name>L_light</name>
        <pose>Unspecified</pose>
        <type>rect</type>
        <truncated>0</truncated>
        <difficult>0</difficult>
        <text>1</text>
        <model>3</model>
        <bndbox>
            <xmin>206</xmin>
            <ymin>301</ymin>
            <xmax>219</xmax>
            <ymax>306</ymax>
        </bndbox>
        <width>13</width>
        <height>5</height>
    </object>
    <object>
        <name>R_light</name>
        <pose>Unspecified</pose>
        <type>rect</type>
        <truncated>0</truncated>
        <difficult>0</difficult>
        <text>1</text>
        <model>3</model>
        <bndbox>
            <xmin>244</xmin>
            <ymin>301</ymin>
            <xmax>259</xmax>
            <ymax>306</ymax>
        </bndbox>
        <width>15</width>
        <height>5</height>
    </object>
    <object>
        <name>T_light</name>
        <pose>Unspecified</pose>
        <type>rect</type>
        <truncated>0</truncated>
        <difficult>0</difficult>
        <text>1</text>
        <model>3</model>
        <bndbox>
            <xmin>229</xmin>
            <ymin>289</ymin>
            <xmax>237</xmax>
            <ymax>291</ymax>
        </bndbox>
        <width>9</width>
        <height>2</height>
    </object>
    <object>
        <name>day-left</name>
        <pose>Unspecified</pose>
        <type>rect</type>
        <truncated>0</truncated>
        <difficult>0</difficult>
        <text>2</text>
        <model>3</model>
        <bndbox>
            <xmin>321</xmin>
            <ymin>285</ymin>
            <xmax>473</xmax>
            <ymax>411</ymax>
        </bndbox>
        <width>152</width>
        <height>126</height>
    </object>
    <object>
        <name>L_light</name>
        <pose>Unspecified</pose>
        <type>rect</type>
        <truncated>0</truncated>
        <difficult>0</difficult>
        <text>2</text>
        <model>3</model>
        <bndbox>
            <xmin>327</xmin>
            <ymin>323</ymin>
            <xmax>373</xmax>
            <ymax>343</ymax>
        </bndbox>
        <width>46</width>
        <height>20</height>
    </object>
    <object>
        <name>R_light</name>
        <pose>Unspecified</pose>
        <type>rect</type>
        <truncated>0</truncated>
        <difficult>0</difficult>
        <text>2</text>
        <model>3</model>
        <bndbox>
            <xmin>432</xmin>
            <ymin>327</ymin>
            <xmax>472</xmax>
            <ymax>344</ymax>
        </bndbox>
        <width>39</width>
        <height>18</height>
    </object>
    <object>
        <name>T_light</name>
        <pose>Unspecified</pose>
        <type>rect</type>
        <truncated>0</truncated>
        <difficult>0</difficult>
        <text>2</text>
        <model>3</model>
        <bndbox>
            <xmin>391</xmin>
            <ymin>293</ymin>
            <xmax>408</xmax>
            <ymax>297</ymax>
        </bndbox>
        <width>17</width>
        <height>5</height>
    </object>
    <object>
        <name>plate_1</name>
        <pose>Unspecified</pose>
        <type>rect</type>
        <truncated>0</truncated>
        <difficult>0</difficult>
        <text>
        </text>
        <bndbox>
            <xmin>383</xmin>
            <ymin>334</ymin>
            <xmax>423</xmax>
            <ymax>350</ymax>
        </bndbox>
        <width>40</width>
        <height>16</height>
    </object>
</annotation>
