<?xml version='1.0' encoding='utf-8'?>
<annotation>
    <folder>/待标.zip/待标</folder>
    <filename>4737.jpg</filename>
    <path>/待标.zip/待标</path>
    <source>
        <database>Unknown</database>
    </source>
    <amount>4</amount>
    <size>
        <width>1920</width>
        <height>1000</height>
        <depth>3</depth>
    </size>
    <segmented>0</segmented>
    <object>
        <name>day-right</name>
        <pose>Unspecified</pose>
        <type>rect</type>
        <truncated>0</truncated>
        <difficult>0</difficult>
        <text>1</text>
        <model>3</model>
        <bndbox>
            <xmin>991</xmin>
            <ymin>325</ymin>
            <xmax>1071</xmax>
            <ymax>398</ymax>
        </bndbox>
        <width>80</width>
        <height>73</height>
    </object>
    <object>
        <name>T_light</name>
        <pose>Unspecified</pose>
        <type>rect</type>
        <truncated>0</truncated>
        <difficult>0</difficult>
        <text>1</text>
        <model>3</model>
        <bndbox>
            <xmin>1033</xmin>
            <ymin>328</ymin>
            <xmax>1046</xmax>
            <ymax>332</ymax>
        </bndbox>
        <width>13</width>
        <height>5</height>
    </object>
    <object>
        <name>L_light</name>
        <pose>Unspecified</pose>
        <type>rect</type>
        <truncated>0</truncated>
        <difficult>0</difficult>
        <text>1</text>
        <model>3</model>
        <bndbox>
            <xmin>991</xmin>
            <ymin>350</ymin>
            <xmax>1012</xmax>
            <ymax>360</ymax>
        </bndbox>
        <width>21</width>
        <height>10</height>
    </object>
    <object>
        <name>R_light</name>
        <pose>Unspecified</pose>
        <type>rect</type>
        <truncated>0</truncated>
        <difficult>0</difficult>
        <text>1</text>
        <model>3</model>
        <bndbox>
            <xmin>1044</xmin>
            <ymin>351</ymin>
            <xmax>1070</xmax>
            <ymax>361</ymax>
        </bndbox>
        <width>26</width>
        <height>10</height>
    </object>
</annotation>