<?xml version="1.0" encoding="UTF-8"?>
<annotation>
    <folder>/待标.zip/待标</folder>
    <filename>4738c7.jpg</filename>
    <path>/待标.zip/待标</path>
    <source>
        <database>Unknown</database>
    </source>
    <amount>4</amount>
    <size>
        <width>557</width>
        <height>500</height>
        <depth>3</depth>
    </size>
    <segmented>0</segmented>
    <object>
        <name>day-right</name>
        <pose>Unspecified</pose>
        <type>rect</type>
        <truncated>0</truncated>
        <difficult>0</difficult>
        <text>1</text>
        <model>3</model>
        <bndbox>
            <xmin>173</xmin>
            <ymin>177</ymin>
            <xmax>252</xmax>
            <ymax>250</ymax>
        </bndbox>
        <width>79</width>
        <height>73</height>
    </object>
    <object>
        <name>L_light</name>
        <pose>Unspecified</pose>
        <type>rect</type>
        <truncated>0</truncated>
        <difficult>0</difficult>
        <text>1</text>
        <model>3</model>
        <bndbox>
            <xmin>173</xmin>
            <ymin>200</ymin>
            <xmax>191</xmax>
            <ymax>209</ymax>
        </bndbox>
        <width>18</width>
        <height>9</height>
    </object>
    <object>
        <name>R_light</name>
        <pose>Unspecified</pose>
        <type>rect</type>
        <truncated>0</truncated>
        <difficult>0</difficult>
        <text>1</text>
        <model>3</model>
        <bndbox>
            <xmin>224</xmin>
            <ymin>200</ymin>
            <xmax>251</xmax>
            <ymax>210</ymax>
        </bndbox>
        <width>26</width>
        <height>10</height>
    </object>
    <object>
        <name>T_light</name>
        <pose>Unspecified</pose>
        <type>rect</type>
        <truncated>0</truncated>
        <difficult>0</difficult>
        <text>1</text>
        <model>3</model>
        <bndbox>
            <xmin>213</xmin>
            <ymin>181</ymin>
            <xmax>223</xmax>
            <ymax>184</ymax>
        </bndbox>
        <width>10</width>
        <height>3</height>
    </object>
</annotation>
