<?xml version="1.0" encoding="UTF-8"?>
<annotation>
    <folder>/待标.zip/待标</folder>
    <filename>4791c8.jpg</filename>
    <path>/待标.zip/待标</path>
    <source>
        <database>Unknown</database>
    </source>
    <amount>4</amount>
    <size>
        <width>1046</width>
        <height>423</height>
        <depth>3</depth>
    </size>
    <segmented>0</segmented>
    <object>
        <name>day-left</name>
        <pose>Unspecified</pose>
        <type>rect</type>
        <truncated>0</truncated>
        <difficult>0</difficult>
        <text>1</text>
        <model>3</model>
        <bndbox>
            <xmin>306</xmin>
            <ymin>291</ymin>
            <xmax>369</xmax>
            <ymax>342</ymax>
        </bndbox>
        <width>63</width>
        <height>51</height>
    </object>
    <object>
        <name>T_light</name>
        <pose>Unspecified</pose>
        <type>rect</type>
        <truncated>0</truncated>
        <difficult>0</difficult>
        <text>1</text>
        <model>3</model>
        <bndbox>
            <xmin>333</xmin>
            <ymin>294</ymin>
            <xmax>342</xmax>
            <ymax>297</ymax>
        </bndbox>
        <width>8</width>
        <height>2</height>
    </object>
    <object>
        <name>L_light</name>
        <pose>Unspecified</pose>
        <type>rect</type>
        <truncated>0</truncated>
        <difficult>0</difficult>
        <text>1</text>
        <model>3</model>
        <bndbox>
            <xmin>309</xmin>
            <ymin>308</ymin>
            <xmax>327</xmax>
            <ymax>318</ymax>
        </bndbox>
        <width>19</width>
        <height>10</height>
    </object>
    <object>
        <name>R_light</name>
        <pose>Unspecified</pose>
        <type>rect</type>
        <truncated>0</truncated>
        <difficult>0</difficult>
        <text>1</text>
        <model>3</model>
        <bndbox>
            <xmin>348</xmin>
            <ymin>307</ymin>
            <xmax>366</xmax>
            <ymax>316</ymax>
        </bndbox>
        <width>18</width>
        <height>9</height>
    </object>
</annotation>
